backgroundpy/__init__.py
backgroundpy/__main__.py
backgroundpy-1.0.0.dist-info/LICENSE
backgroundpy-1.0.0.dist-info/METADATA
backgroundpy-1.0.0.dist-info/WHEEL
backgroundpy-1.0.0.dist-info/top_level.txt
backgroundpy-1.0.0.dist-info/RECORD
